trident/__init__.py
trident/config.py
trident/instrument.py
trident/ion_balance.py
trident/light_ray.py
trident/line_database.py
trident/lsf.py
trident/plotting.py
trident/ray_generator.py
trident/roman.py
trident/spectrum_generator.py
trident/testing.py
trident/utilities.py
trident/absorption_spectrum/__init__.py
trident/absorption_spectrum/absorption_line.py
trident/absorption_spectrum/absorption_spectrum.py
trident/absorption_spectrum/absorption_spectrum_fit.py
trident/data/line_lists/lines.txt
trident/data/lsf_kernels/avg_COS.txt
trident/data/lsf_kernels/avg_COS_G130M.txt
trident/data/lsf_kernels/avg_COS_G140L.txt
trident/data/lsf_kernels/avg_COS_G160M.txt
trident/data/spectral_templates/mw_foreground_COS.txt
trident/data/spectral_templates/qso_background_COS_HST.txt
trident-1.4.1.dist-info/LICENSE
trident-1.4.1.dist-info/METADATA
trident-1.4.1.dist-info/WHEEL
trident-1.4.1.dist-info/top_level.txt
trident-1.4.1.dist-info/RECORD
