Metadata-Version: 2.2
Name: trident
Version: 1.4.1
Summary: Package for simulating UV observations from astrophysical sources
Author-email: Cameron Hummels <chummels@gmail.com>
License: BSD 3-Clause
Project-URL: Homepage, https://trident-project.org/
Project-URL: Documentation, https://trident.readthedocs.io
Project-URL: Source, https://github.com/trident-project/trident/
Project-URL: Tracker, https://github.com/trident-project/trident/issues
Keywords: astronomy astrophysics cgm
Classifier: Intended Audience :: Science/Research
Classifier: Operating System :: OS Independent
Classifier: Programming Language :: Python :: 3
Classifier: Topic :: Scientific/Engineering :: Visualization
Classifier: Topic :: Scientific/Engineering :: Astronomy
Classifier: Topic :: Scientific/Engineering :: Physics
Classifier: License :: OSI Approved :: BSD License
Classifier: Natural Language :: English
Classifier: Programming Language :: Python :: 3
Classifier: Programming Language :: Python :: 3.10
Classifier: Programming Language :: Python :: 3.11
Classifier: Programming Language :: Python :: 3.12
Requires-Python: >=3.10
License-File: LICENSE
Requires-Dist: numpy
Requires-Dist: astropy
Requires-Dist: matplotlib
Requires-Dist: h5py
Requires-Dist: scipy
Requires-Dist: tqdm
Requires-Dist: requests
Requires-Dist: yt>=4.4
Requires-Dist: yt_astro_analysis>=1.1.0
